README.md
setup.py
flask_server_timing.egg-info/PKG-INFO
flask_server_timing.egg-info/SOURCES.txt
flask_server_timing.egg-info/dependency_links.txt
flask_server_timing.egg-info/entry_points.txt
flask_server_timing.egg-info/namespace_packages.txt
flask_server_timing.egg-info/requires.txt
flask_server_timing.egg-info/top_level.txt
server_timing/__init__.py