Metadata-Version: 1.1
Name: flask-server-timing
Version: 0.1.2
Summary: Python Flask Server-Timing Header Extension
Home-page: https://github.com/rodrobin/flask-server-timing
Author: Robin Peters
Author-email: github@rpeters.dk
License: Apache License 2.0
Keywords: Python Flask Server-Timing Header Extension
Platform: Linux
Platform: POSIX
Classifier: Programming Language :: Python :: 2.7
Classifier: Programming Language :: Python :: 3
